tenma/__init__.py
tenma/gtkIndicator.py
tenma/logo.png
tenma/tenmaControl.py
tenma/tenmaDcLib.py
tenma_serial-1.1.4.dist-info/licenses/AUTHORS
tenma_serial-1.1.4.dist-info/licenses/LICENSE.txt
tenma_serial-1.1.4.dist-info/METADATA
tenma_serial-1.1.4.dist-info/WHEEL
tenma_serial-1.1.4.dist-info/entry_points.txt
tenma_serial-1.1.4.dist-info/pbr.json
tenma_serial-1.1.4.dist-info/top_level.txt
tenma_serial-1.1.4.dist-info/RECORD
