Metadata-Version: 2.4
Name: tenma-serial
Version: 1.1.4
Summary: Serial control of tenma device
Home-page: https://github.com/kxtells/tenma-serial
Author: Jordi Castells
Author-email: jordi.kstells@gmail.com
License: GNU-3
Project-URL: Documentation, https://tenma-serial.readthedocs.io/en/latest/
Classifier: Development Status :: 4 - Beta
Classifier: Environment :: Console
Classifier: Environment :: X11 Applications :: GTK
Classifier: Intended Audience :: Developers
Classifier: Intended Audience :: Information Technology
Classifier: License :: OSI Approved :: GNU General Public License v3 (GPLv3)
Classifier: Operating System :: OS Independent
Classifier: Programming Language :: Python
License-File: LICENSE.txt
License-File: AUTHORS
Requires-Dist: pyserial
Dynamic: author
Dynamic: author-email
Dynamic: classifier
Dynamic: description
Dynamic: description-content-type
Dynamic: home-page
Dynamic: license
Dynamic: license-file
Dynamic: project-url
Dynamic: requires-dist
Dynamic: summary
